{
  "items": [
    {
      "id": "src-tx-0000",
      "label": "High Risk",
      "linked_transaction_id": "tx-0000",
      "reason_codes": [
        "proposal frequency spike",
        "new destination behavior"
      ],
      "risk_score": 81.28,
      "severity": "high",
      "source_key": "tx-0000",
      "title": "Behavior Manipulation Risk Detected"
    },
    {
      "id": "src-tx-0001",
      "label": "Clean",
      "linked_transaction_id": "tx-0001",
      "reason_codes": [
        "proposal frequency spike",
        "unusually large proposal size"
      ],
      "risk_score": 30.02,
      "severity": "low",
      "source_key": "tx-0001",
      "title": "Behavior Manipulation Risk Detected"
    },
    {
      "id": "src-tx-0002",
      "label": "Clean",
      "linked_transaction_id": "tx-0002",
      "reason_codes": [],
      "risk_score": 10.45,
      "severity": "low",
      "source_key": "tx-0002",
      "title": "Behavior Manipulation Risk Detected"
    },
    {
      "id": "src-tx-0003",
      "label": "High Risk",
      "linked_transaction_id": "tx-0003",
      "reason_codes": [
        "proposal frequency spike",
        "new destination behavior"
      ],
      "risk_score": 74.02,
      "severity": "high",
      "source_key": "tx-0003",
      "title": "Behavior Manipulation Risk Detected"
    },
    {
      "id": "src-tx-0004",
      "label": "Suspicious",
      "linked_transaction_id": "tx-0004",
      "reason_codes": [
        "proposal frequency spike",
        "unusually large proposal size"
      ],
      "risk_score": 45.2,
      "severity": "medium",
      "source_key": "tx-0004",
      "title": "Behavior Manipulation Risk Detected"
    },
    {
      "id": "src-tx-0005",
      "label": "Clean",
      "linked_transaction_id": "tx-0005",
      "reason_codes": [
        "proposal frequency spike"
      ],
      "risk_score": 31.94,
      "severity": "low",
      "source_key": "tx-0005",
      "title": "Behavior Manipulation Risk Detected"
    },
    {
      "id": "src-tx-0006",
      "label": "Suspicious",
      "linked_transaction_id": "tx-0006",
      "reason_codes": [
        "proposal frequency spike",
        "unusually large proposal size"
      ],
      "risk_score": 58.67,
      "severity": "medium",
      "source_key": "tx-0006",
      "title": "Behavior Manipulation Risk Detected"
    },
    {
      "id": "src-tx-0007",
      "label": "Suspicious",
      "linked_transaction_id": "tx-0007",
      "reason_codes": [
        "proposal frequency spike",
        "unusually large proposal size"
      ],
      "risk_score": 51.64,
      "severity": "medium",
      "source_key": "tx-0007",
      "title": "Behavior Manipulation Risk Detected"
    }
  ],
  "module": "behavior_manipulation",
  "updated_at": "2026-07-07T04:06:22Z"
}