{
  "items": [
    {
      "amount": 10.96,
      "day_of_week": 2,
      "features_used": [
        "id",
        "amount",
        "token_type",
        "hour",
        "day_of_week",
        "gas_fee",
        "is_new_address",
        "time_since_last_tx",
        "tx_frequency"
      ],
      "gas_fee": 27.74,
      "hour": 20,
      "id": "tx-0000",
      "is_new_address": 0,
      "label": "Suspicious",
      "risk_score": 35.17,
      "severity": "medium",
      "time_since_last_tx": 34,
      "token_type": 0,
      "tx_frequency": 1
    },
    {
      "amount": 45.5,
      "day_of_week": 2,
      "features_used": [
        "id",
        "amount",
        "token_type",
        "hour",
        "day_of_week",
        "gas_fee",
        "is_new_address",
        "time_since_last_tx",
        "tx_frequency"
      ],
      "gas_fee": 58.12,
      "hour": 22,
      "id": "tx-0001",
      "is_new_address": 1,
      "label": "High Risk",
      "risk_score": 84.64,
      "severity": "high",
      "time_since_last_tx": 125,
      "token_type": 1,
      "tx_frequency": 7
    },
    {
      "amount": 44.29,
      "day_of_week": 0,
      "features_used": [
        "id",
        "amount",
        "token_type",
        "hour",
        "day_of_week",
        "gas_fee",
        "is_new_address",
        "time_since_last_tx",
        "tx_frequency"
      ],
      "gas_fee": 29.13,
      "hour": 23,
      "id": "tx-0002",
      "is_new_address": 0,
      "label": "Suspicious",
      "risk_score": 48.48,
      "severity": "medium",
      "time_since_last_tx": 96,
      "token_type": 0,
      "tx_frequency": 4
    },
    {
      "amount": 43.3,
      "day_of_week": 6,
      "features_used": [
        "id",
        "amount",
        "token_type",
        "hour",
        "day_of_week",
        "gas_fee",
        "is_new_address",
        "time_since_last_tx",
        "tx_frequency"
      ],
      "gas_fee": 14.42,
      "hour": 20,
      "id": "tx-0003",
      "is_new_address": 1,
      "label": "High Risk",
      "risk_score": 73.11,
      "severity": "high",
      "time_since_last_tx": 508,
      "token_type": 2,
      "tx_frequency": 18
    },
    {
      "amount": 48.04,
      "day_of_week": 3,
      "features_used": [
        "id",
        "amount",
        "token_type",
        "hour",
        "day_of_week",
        "gas_fee",
        "is_new_address",
        "time_since_last_tx",
        "tx_frequency"
      ],
      "gas_fee": 19.01,
      "hour": 8,
      "id": "tx-0004",
      "is_new_address": 0,
      "label": "Clean",
      "risk_score": 0.0,
      "severity": "low",
      "time_since_last_tx": 824,
      "token_type": 2,
      "tx_frequency": 12
    },
    {
      "amount": 44.51,
      "day_of_week": 0,
      "features_used": [
        "id",
        "amount",
        "token_type",
        "hour",
        "day_of_week",
        "gas_fee",
        "is_new_address",
        "time_since_last_tx",
        "tx_frequency"
      ],
      "gas_fee": 67.51,
      "hour": 13,
      "id": "tx-0005",
      "is_new_address": 0,
      "label": "Clean",
      "risk_score": 24.99,
      "severity": "low",
      "time_since_last_tx": 192,
      "token_type": 0,
      "tx_frequency": 11
    },
    {
      "amount": 5.73,
      "day_of_week": 0,
      "features_used": [
        "id",
        "amount",
        "token_type",
        "hour",
        "day_of_week",
        "gas_fee",
        "is_new_address",
        "time_since_last_tx",
        "tx_frequency"
      ],
      "gas_fee": 56.1,
      "hour": 10,
      "id": "tx-0006",
      "is_new_address": 0,
      "label": "Clean",
      "risk_score": 10.0,
      "severity": "low",
      "time_since_last_tx": 176,
      "token_type": 2,
      "tx_frequency": 10
    },
    {
      "amount": 12.44,
      "day_of_week": 4,
      "features_used": [
        "id",
        "amount",
        "token_type",
        "hour",
        "day_of_week",
        "gas_fee",
        "is_new_address",
        "time_since_last_tx",
        "tx_frequency"
      ],
      "gas_fee": 24.37,
      "hour": 12,
      "id": "tx-0007",
      "is_new_address": 1,
      "label": "Suspicious",
      "risk_score": 62.28,
      "severity": "medium",
      "time_since_last_tx": 291,
      "token_type": 1,
      "tx_frequency": 5
    }
  ],
  "module": "transaction_anomaly",
  "updated_at": "2026-07-03T23:51:24Z"
}